redpic/__init__.py
redpic/accelerator.py
redpic/beam.py
redpic/constants.py
redpic/solver.py
redpic-1.0.0.2.dist-info/LICENSE
redpic-1.0.0.2.dist-info/METADATA
redpic-1.0.0.2.dist-info/WHEEL
redpic-1.0.0.2.dist-info/top_level.txt
redpic-1.0.0.2.dist-info/RECORD
