Metadata-Version: 2.1
Name: redpic
Version: 1.0.0.2
Summary: Relativictic Difference Scheme Particle-in-Cell code (REDPIC)
Home-page: https://github.com/fuodorov/redpic
Author: Vyacheslav Fedorov
Author-email: slava@fuodorov.ru
License: UNKNOWN
Platform: UNKNOWN
Classifier: Programming Language :: Python :: 3
Classifier: License :: OSI Approved :: MIT License
Classifier: Operating System :: OS Independent
Classifier: Intended Audience :: Science/Research
Classifier: Topic :: Scientific/Engineering :: Physics
